fragment_pkg/__init__.py
frag_lib-1.0.0.dist-info/LICENSE
frag_lib-1.0.0.dist-info/METADATA
frag_lib-1.0.0.dist-info/WHEEL
frag_lib-1.0.0.dist-info/top_level.txt
frag_lib-1.0.0.dist-info/RECORD
