Metadata-Version: 2.1
Name: frag-lib
Version: 1.0.0
Summary: Fragment library package
Home-page: https://github.com/hemahecodes/fragment_library
Author: Helena Martin
Author-email: helena.martin@nostrumbiodiscovery.com
License: UNKNOWN
Platform: UNKNOWN
Classifier: Programming Language :: Python :: 3
Classifier: License :: OSI Approved :: MIT License
Classifier: Operating System :: OS Independent
Requires-Python: >=3.6
